pysciebo/__init__.py
pysciebo/cmd.py
pysciebo-1.1.0.dist-info/entry_points.txt
pysciebo-1.1.0.dist-info/LICENSE.txt
pysciebo-1.1.0.dist-info/WHEEL
pysciebo-1.1.0.dist-info/METADATA
pysciebo-1.1.0.dist-info/RECORD
