Metadata-Version: 2.1
Name: pysciebo
Version: 1.1.0
Summary: A Python client for sciebo aka hochschulcloud.nrw
Home-page: https://gitlab.ub.uni-bielefeld.de/nils.mueller/pysciebo
License: MIT
Author: Nils Müller
Author-email: nils.mueller@uni-bielefeld.de
Requires-Python: >=3.9,<4.0
Classifier: License :: OSI Approved :: MIT License
Classifier: Programming Language :: Python :: 3
Classifier: Programming Language :: Python :: 3.9
Requires-Dist: click (>=8.0.3,<9.0.0)
Requires-Dist: pyocclient (>=0.6,<0.7)
Project-URL: Repository, https://gitlab.ub.uni-bielefeld.de/nils.mueller/pysciebo
